pyp6xer_mcp/__init__.py
pyp6xer_mcp/cli.py
pyp6xer_mcp/server.py
pyp6xer_mcp/context/__init__.py
pyp6xer_mcp/context/xer_context.py
pyp6xer_mcp/core/__init__.py
pyp6xer_mcp/core/cache.py
pyp6xer_mcp/core/formatters.py
pyp6xer_mcp/core/helpers.py
pyp6xer_mcp/http/__init__.py
pyp6xer_mcp/http/middleware.py
pyp6xer_mcp/http/routes.py
pyp6xer_mcp/models/__init__.py
pyp6xer_mcp/models/activities.py
pyp6xer_mcp/models/analysis.py
pyp6xer_mcp/models/common.py
pyp6xer_mcp/models/file_ops.py
pyp6xer_mcp/models/resources.py
pyp6xer_mcp/prompts/__init__.py
pyp6xer_mcp/prompts/analysis.py
pyp6xer_mcp/resources/__init__.py
pyp6xer_mcp/resources/schedule.py
pyp6xer_mcp/tools/__init__.py
pyp6xer_mcp/tools/activities.py
pyp6xer_mcp/tools/analysis.py
pyp6xer_mcp/tools/calendars.py
pyp6xer_mcp/tools/file_ops.py
pyp6xer_mcp/tools/progress.py
pyp6xer_mcp/tools/projects.py
pyp6xer_mcp/tools/resources.py
pyp6xer_mcp-1.0.0.dist-info/METADATA
pyp6xer_mcp-1.0.0.dist-info/WHEEL
pyp6xer_mcp-1.0.0.dist-info/entry_points.txt
pyp6xer_mcp-1.0.0.dist-info/licenses/LICENSE
pyp6xer_mcp-1.0.0.dist-info/RECORD
